[
    {
        "world": "0018",
        "topic": "clone",
        "source": "00140",
        "target": "00140",
        "operations": [
            {
                "type": "modify",
                "from": {
                    "u": "502.2",
                    "v": "226.2"
                },
                "to": {
                    "u": "491.9",
                    "v": "229.9",
                    "roi": [
                        0,
                        0,
                        0,
                        0
                    ]
                },
                "zoom": "1.0938023539779538",
                "ry": "-0.02539698347606656"
            }
        ]
    },
    {
        "world": "0018",
        "topic": "clone",
        "source": "00141",
        "target": "00141",
        "operations": [
            {
                "type": "modify",
                "from": {
                    "u": "500.7",
                    "v": "227.0"
                },
                "to": {
                    "u": "494.0",
                    "v": "229.7",
                    "roi": [
                        0,
                        0,
                        0,
                        0
                    ]
                },
                "zoom": "1.066474378309581",
                "ry": "-0.05399845683485904"
            }
        ]
    },
    {
        "world": "0018",
        "topic": "clone",
        "source": "00142",
        "target": "00142",
        "operations": [
            {
                "type": "modify",
                "from": {
                    "u": "499.1",
                    "v": "227.3"
                },
                "to": {
                    "u": "495.3",
                    "v": "228.9",
                    "roi": [
                        0,
                        0,
                        0,
                        0
                    ]
                },
                "zoom": "1.0401623661922752",
                "ry": "-0.13869577332340022"
            }
        ]
    },
    {
        "world": "0018",
        "topic": "clone",
        "source": "00143",
        "target": "00143",
        "operations": [
            {
                "type": "modify",
                "from": {
                    "u": "497.7",
                    "v": "227.5"
                },
                "to": {
                    "u": "495.0",
                    "v": "228.1",
                    "roi": [
                        0,
                        0,
                        0,
                        0
                    ]
                },
                "zoom": "1.01590158250917",
                "ry": "-0.269173997202272"
            }
        ]
    },
    {
        "world": "0018",
        "topic": "clone",
        "source": "00144",
        "target": "00144",
        "operations": [
            {
                "type": "modify",
                "from": {
                    "u": "496.8",
                    "v": "227.4"
                },
                "to": {
                    "u": "492.8",
                    "v": "227.1",
                    "roi": [
                        0,
                        0,
                        0,
                        0
                    ]
                },
                "zoom": "0.9925267109888055",
                "ry": "-0.42337728895924"
            }
        ]
    },
    {
        "world": "0018",
        "topic": "clone",
        "source": "00145",
        "target": "00145",
        "operations": [
            {
                "type": "modify",
                "from": {
                    "u": "495.9",
                    "v": "227.6"
                },
                "to": {
                    "u": "488.3",
                    "v": "226.4",
                    "roi": [
                        0,
                        0,
                        0,
                        0
                    ]
                },
                "zoom": "0.9699999837406932",
                "ry": "-0.5756916866180519"
            }
        ]
    },
    {
        "world": "0018",
        "topic": "clone",
        "source": "00146",
        "target": "00146",
        "operations": [
            {
                "type": "modify",
                "from": {
                    "u": "495.0",
                    "v": "228.2"
                },
                "to": {
                    "u": "481.5",
                    "v": "226.1",
                    "roi": [
                        0,
                        0,
                        0,
                        0
                    ]
                },
                "zoom": "0.9482782418471469",
                "ry": "-0.7066739651403853"
            }
        ]
    },
    {
        "world": "0018",
        "topic": "clone",
        "source": "00147",
        "target": "00147",
        "operations": [
            {
                "type": "modify",
                "from": {
                    "u": "494.0",
                    "v": "228.6"
                },
                "to": {
                    "u": "472.6",
                    "v": "225.5",
                    "roi": [
                        0,
                        0,
                        0,
                        0
                    ]
                },
                "zoom": "0.9273182568393273",
                "ry": "-0.8081131468735148"
            }
        ]
    },
    {
        "world": "0018",
        "topic": "clone",
        "source": "00148",
        "target": "00148",
        "operations": [
            {
                "type": "modify",
                "from": {
                    "u": "493.5",
                    "v": "228.8"
                },
                "to": {
                    "u": "461.9",
                    "v": "225.0",
                    "roi": [
                        0,
                        0,
                        0,
                        0
                    ]
                },
                "zoom": "0.9086978390178265",
                "ry": "-0.8799588552478519"
            }
        ]
    },
    {
        "world": "0018",
        "topic": "clone",
        "source": "00149",
        "target": "00149",
        "operations": [
            {
                "type": "modify",
                "from": {
                    "u": "492.9",
                    "v": "229.0"
                },
                "to": {
                    "u": "449.9",
                    "v": "224.4",
                    "roi": [
                        0,
                        0,
                        0,
                        0
                    ]
                },
                "zoom": "0.8906998229033315",
                "ry": "-0.9252378172816438"
            }
        ]
    },
    {
        "world": "0018",
        "topic": "clone",
        "source": "00150",
        "target": "00150",
        "operations": [
            {
                "type": "modify",
                "from": {
                    "u": "492.4",
                    "v": "229.4"
                },
                "to": {
                    "u": "437.4",
                    "v": "224.0",
                    "roi": [
                        0,
                        0,
                        0,
                        0
                    ]
                },
                "zoom": "0.8732851747669179",
                "ry": "-0.9469669910615837"
            }
        ]
    },
    {
        "world": "0018",
        "topic": "clone",
        "source": "00151",
        "target": "00151",
        "operations": [
            {
                "type": "modify",
                "from": {
                    "u": "492.4",
                    "v": "229.4"
                },
                "to": {
                    "u": "424.9",
                    "v": "223.3",
                    "roi": [
                        0,
                        0,
                        0,
                        0
                    ]
                },
                "zoom": "0.8564161703251691",
                "ry": "-0.9468199910615842"
            }
        ]
    },
    {
        "world": "0018",
        "topic": "clone",
        "source": "00152",
        "target": "00152",
        "operations": [
            {
                "type": "modify",
                "from": {
                    "u": "491.9",
                    "v": "229.1"
                },
                "to": {
                    "u": "413.1",
                    "v": "222.4",
                    "roi": [
                        0,
                        0,
                        0,
                        0
                    ]
                },
                "zoom": "0.8400577360217863",
                "ry": "-0.9248248172816442"
            }
        ]
    },
    {
        "world": "0018",
        "topic": "clone",
        "source": "00153",
        "target": "00153",
        "operations": [
            {
                "type": "modify",
                "from": {
                    "u": "491.9",
                    "v": "229.3"
                },
                "to": {
                    "u": "402.6",
                    "v": "221.9",
                    "roi": [
                        0,
                        0,
                        0,
                        0
                    ]
                },
                "zoom": "0.8244277978355313",
                "ry": "-0.8792958552478514"
            }
        ]
    },
    {
        "world": "0018",
        "topic": "clone",
        "source": "00154",
        "target": "00154",
        "operations": [
            {
                "type": "modify",
                "from": {
                    "u": "491.9",
                    "v": "229.8"
                },
                "to": {
                    "u": "393.9",
                    "v": "221.6",
                    "roi": [
                        0,
                        0,
                        0,
                        0
                    ]
                },
                "zoom": "0.8092306098237122",
                "ry": "-0.8072281468735152"
            }
        ]
    },
    {
        "world": "0018",
        "topic": "clone",
        "source": "00155",
        "target": "00155",
        "operations": [
            {
                "type": "modify",
                "from": {
                    "u": "491.9",
                    "v": "230.1"
                },
                "to": {
                    "u": "387.3",
                    "v": "221.2",
                    "roi": [
                        0,
                        0,
                        0,
                        0
                    ]
                },
                "zoom": "0.7944480025200596",
                "ry": "-0.7055409651403852"
            }
        ]
    },
    {
        "world": "0018",
        "topic": "clone",
        "source": "00156",
        "target": "00156",
        "operations": [
            {
                "type": "modify",
                "from": {
                    "u": "492.0",
                    "v": "230.5"
                },
                "to": {
                    "u": "383.0",
                    "v": "220.9",
                    "roi": [
                        0,
                        0,
                        0,
                        0
                    ]
                },
                "zoom": "0.7800827986815446",
                "ry": "-0.5743186866180519"
            }
        ]
    },
    {
        "world": "0018",
        "topic": "clone",
        "source": "00157",
        "target": "00157",
        "operations": [
            {
                "type": "modify",
                "from": {
                    "u": "491.9",
                    "v": "231.5"
                },
                "to": {
                    "u": "380.8",
                    "v": "221.1",
                    "roi": [
                        0,
                        0,
                        0,
                        0
                    ]
                },
                "zoom": "0.7660686173200146",
                "ry": "-0.42178728895924"
            }
        ]
    },
    {
        "world": "0018",
        "topic": "clone",
        "source": "00158",
        "target": "00158",
        "operations": [
            {
                "type": "modify",
                "from": {
                    "u": "492.0",
                    "v": "232.5"
                },
                "to": {
                    "u": "380.6",
                    "v": "221.2",
                    "roi": [
                        0,
                        0,
                        0,
                        0
                    ]
                },
                "zoom": "0.7524465930418993",
                "ry": "-0.2673569972022718"
            }
        ]
    },
    {
        "world": "0018",
        "topic": "clone",
        "source": "00159",
        "target": "00159",
        "operations": [
            {
                "type": "modify",
                "from": {
                    "u": "491.9",
                    "v": "232.6"
                },
                "to": {
                    "u": "382.0",
                    "v": "220.7",
                    "roi": [
                        0,
                        0,
                        0,
                        0
                    ]
                },
                "zoom": "0.7391707672889443",
                "ry": "-0.13663277332340096"
            }
        ]
    }
]